{"_id":{"$oid":"5bb91933da9bf5bac14ab6f5"},"title":"EXTREME HIIT #2 Workout","difficulty":"hard","workout":[{"_id":{"$oid":"5bb91933da9bf5bac14ab6fb"},"name":"Bar row","sets":"4","reps":"12"},{"_id":{"$oid":"5bb91933da9bf5bac14ab6fa"},"name":"Incline Bench Press","sets":"3","reps":"12"},{"_id":{"$oid":"5bb91933da9bf5bac14ab6f9"},"name":"Incline Dumbbell Flyes","sets":"3","reps":"12"},{"_id":{"$oid":"5bb91933da9bf5bac14ab6f8"},"name":"Cable Crossover","sets":"3","reps":"12"},{"_id":{"$oid":"5bb91933da9bf5bac14ab6f7"},"name":"Triceps Pushdown","sets":"4","reps":"12"},{"_id":{"$oid":"5bb91933da9bf5bac14ab6f6"},"name":"Laying Dumbbell Tricep Extension","sets":"4","reps":"12"}],"creator":{"$oid":"5b9ea478fec0802340915545"},"__v":0}
